MANIFEST.in
README.rst
selwsgi.py
setup.py
selwsgi.egg-info/PKG-INFO
selwsgi.egg-info/SOURCES.txt
selwsgi.egg-info/dependency_links.txt
selwsgi.egg-info/requires.txt
selwsgi.egg-info/top_level.txt