Metadata-Version: 1.1
Name: selwsgi
Version: 0.1
Summary: A simple library to wrap wsgi apps in an evironment suitable to be unit tested with Selenium WebDriver
Home-page: https://github.com/freyes/selenium-webdriver-wsgi
Author: Felipe Reyes
Author-email: freyes@tty.cl
License: MIT
Keywords: selenium wsgi webtest unittest
Platform: UNKNOWN
Classifier: Intended Audience :: Developers
Classifier: License :: OSI Approved :: MIT License
Classifier: Topic :: Internet :: WWW/HTTP :: WSGI
Classifier: Topic :: Internet :: WWW/HTTP :: WSGI :: Server
Classifier: Programming Language :: Python :: 2.5
Classifier: Programming Language :: Python :: 2.6
Classifier: Programming Language :: Python :: 2.7
